{
	"configurations" : 
	[
		{
			"directories" : 
			[
				{
					"build" : ".",
					"childIndexes" : 
					[
						1,
						2,
						3,
						4,
						5
					],
					"hasInstallRule" : true,
					"jsonFile" : "directory-.-Release-337fe4d237cff9c431f5.json",
					"minimumCMakeVersion" : 
					{
						"string" : "3.12"
					},
					"projectIndex" : 0,
					"source" : ".",
					"targetIndexes" : 
					[
						12,
						19
					]
				},
				{
					"build" : "rviz_plugin_render_tools",
					"hasInstallRule" : true,
					"jsonFile" : "directory-rviz_plugin_render_tools-Release-ed7fbc9f2a30e68a893a.json",
					"minimumCMakeVersion" : 
					{
						"string" : "3.12"
					},
					"parentIndex" : 0,
					"projectIndex" : 0,
					"source" : "rviz_plugin_render_tools",
					"targetIndexes" : 
					[
						13,
						14
					]
				},
				{
					"build" : "robot_state_rviz_plugin",
					"hasInstallRule" : true,
					"jsonFile" : "directory-robot_state_rviz_plugin-Release-5f75891e8cd150b324a2.json",
					"minimumCMakeVersion" : 
					{
						"string" : "3.12"
					},
					"parentIndex" : 0,
					"projectIndex" : 0,
					"source" : "robot_state_rviz_plugin",
					"targetIndexes" : 
					[
						8,
						9,
						10,
						11
					]
				},
				{
					"build" : "planning_scene_rviz_plugin",
					"hasInstallRule" : true,
					"jsonFile" : "directory-planning_scene_rviz_plugin-Release-3f685c8a138fb0e44c6c.json",
					"minimumCMakeVersion" : 
					{
						"string" : "3.12"
					},
					"parentIndex" : 0,
					"projectIndex" : 0,
					"source" : "planning_scene_rviz_plugin",
					"targetIndexes" : 
					[
						4,
						5,
						6,
						7
					]
				},
				{
					"build" : "motion_planning_rviz_plugin",
					"hasInstallRule" : true,
					"jsonFile" : "directory-motion_planning_rviz_plugin-Release-c1c480d7a46ee07ff19c.json",
					"minimumCMakeVersion" : 
					{
						"string" : "3.12"
					},
					"parentIndex" : 0,
					"projectIndex" : 0,
					"source" : "motion_planning_rviz_plugin",
					"targetIndexes" : 
					[
						0,
						1,
						2,
						3
					]
				},
				{
					"build" : "trajectory_rviz_plugin",
					"hasInstallRule" : true,
					"jsonFile" : "directory-trajectory_rviz_plugin-Release-1b3a25f294a9327a8e29.json",
					"minimumCMakeVersion" : 
					{
						"string" : "3.12"
					},
					"parentIndex" : 0,
					"projectIndex" : 0,
					"source" : "trajectory_rviz_plugin",
					"targetIndexes" : 
					[
						15,
						16,
						17,
						18
					]
				}
			],
			"name" : "Release",
			"projects" : 
			[
				{
					"directoryIndexes" : 
					[
						0,
						1,
						2,
						3,
						4,
						5
					],
					"name" : "moveit_ros_visualization",
					"targetIndexes" : 
					[
						0,
						1,
						2,
						3,
						4,
						5,
						6,
						7,
						8,
						9,
						10,
						11,
						12,
						13,
						14,
						15,
						16,
						17,
						18,
						19
					]
				}
			],
			"targets" : 
			[
				{
					"directoryIndex" : 4,
					"id" : "moveit_motion_planning_rviz_plugin::@52165aa309b6597994f1",
					"jsonFile" : "target-moveit_motion_planning_rviz_plugin-Release-2171ce209001468f8d12.json",
					"name" : "moveit_motion_planning_rviz_plugin",
					"projectIndex" : 0
				},
				{
					"directoryIndex" : 4,
					"id" : "moveit_motion_planning_rviz_plugin_autogen::@52165aa309b6597994f1",
					"jsonFile" : "target-moveit_motion_planning_rviz_plugin_autogen-Release-43f8a424704806694855.json",
					"name" : "moveit_motion_planning_rviz_plugin_autogen",
					"projectIndex" : 0
				},
				{
					"directoryIndex" : 4,
					"id" : "moveit_motion_planning_rviz_plugin_core::@52165aa309b6597994f1",
					"jsonFile" : "target-moveit_motion_planning_rviz_plugin_core-Release-bccc8aabe501c25f481d.json",
					"name" : "moveit_motion_planning_rviz_plugin_core",
					"projectIndex" : 0
				},
				{
					"directoryIndex" : 4,
					"id" : "moveit_motion_planning_rviz_plugin_core_autogen::@52165aa309b6597994f1",
					"jsonFile" : "target-moveit_motion_planning_rviz_plugin_core_autogen-Release-d0b0ee57bf9785bd654c.json",
					"name" : "moveit_motion_planning_rviz_plugin_core_autogen",
					"projectIndex" : 0
				},
				{
					"directoryIndex" : 3,
					"id" : "moveit_planning_scene_rviz_plugin::@0526de66a6d4fe5c596d",
					"jsonFile" : "target-moveit_planning_scene_rviz_plugin-Release-4b1b2307aeb56e3e1ed8.json",
					"name" : "moveit_planning_scene_rviz_plugin",
					"projectIndex" : 0
				},
				{
					"directoryIndex" : 3,
					"id" : "moveit_planning_scene_rviz_plugin_autogen::@0526de66a6d4fe5c596d",
					"jsonFile" : "target-moveit_planning_scene_rviz_plugin_autogen-Release-7a6ccfb6be983ea99473.json",
					"name" : "moveit_planning_scene_rviz_plugin_autogen",
					"projectIndex" : 0
				},
				{
					"directoryIndex" : 3,
					"id" : "moveit_planning_scene_rviz_plugin_core::@0526de66a6d4fe5c596d",
					"jsonFile" : "target-moveit_planning_scene_rviz_plugin_core-Release-b22dc6c8be2a836c4daa.json",
					"name" : "moveit_planning_scene_rviz_plugin_core",
					"projectIndex" : 0
				},
				{
					"directoryIndex" : 3,
					"id" : "moveit_planning_scene_rviz_plugin_core_autogen::@0526de66a6d4fe5c596d",
					"jsonFile" : "target-moveit_planning_scene_rviz_plugin_core_autogen-Release-57ff8b2feefd7db3ceb6.json",
					"name" : "moveit_planning_scene_rviz_plugin_core_autogen",
					"projectIndex" : 0
				},
				{
					"directoryIndex" : 2,
					"id" : "moveit_robot_state_rviz_plugin::@3cccd1ee7f0cc842f242",
					"jsonFile" : "target-moveit_robot_state_rviz_plugin-Release-566b16bfde3aacb16cc8.json",
					"name" : "moveit_robot_state_rviz_plugin",
					"projectIndex" : 0
				},
				{
					"directoryIndex" : 2,
					"id" : "moveit_robot_state_rviz_plugin_autogen::@3cccd1ee7f0cc842f242",
					"jsonFile" : "target-moveit_robot_state_rviz_plugin_autogen-Release-4bd429c99284c77ed893.json",
					"name" : "moveit_robot_state_rviz_plugin_autogen",
					"projectIndex" : 0
				},
				{
					"directoryIndex" : 2,
					"id" : "moveit_robot_state_rviz_plugin_core::@3cccd1ee7f0cc842f242",
					"jsonFile" : "target-moveit_robot_state_rviz_plugin_core-Release-9406c1e942fde52f867a.json",
					"name" : "moveit_robot_state_rviz_plugin_core",
					"projectIndex" : 0
				},
				{
					"directoryIndex" : 2,
					"id" : "moveit_robot_state_rviz_plugin_core_autogen::@3cccd1ee7f0cc842f242",
					"jsonFile" : "target-moveit_robot_state_rviz_plugin_core_autogen-Release-4a130860d2d5f55dde8a.json",
					"name" : "moveit_robot_state_rviz_plugin_core_autogen",
					"projectIndex" : 0
				},
				{
					"directoryIndex" : 0,
					"id" : "moveit_ros_visualization_uninstall::@6890427a1f51a3e7e1df",
					"jsonFile" : "target-moveit_ros_visualization_uninstall-Release-d80715ebd4a8c8296640.json",
					"name" : "moveit_ros_visualization_uninstall",
					"projectIndex" : 0
				},
				{
					"directoryIndex" : 1,
					"id" : "moveit_rviz_plugin_render_tools::@11af576cd519c4ccae31",
					"jsonFile" : "target-moveit_rviz_plugin_render_tools-Release-b209ba94c63cea15e92d.json",
					"name" : "moveit_rviz_plugin_render_tools",
					"projectIndex" : 0
				},
				{
					"directoryIndex" : 1,
					"id" : "moveit_rviz_plugin_render_tools_autogen::@11af576cd519c4ccae31",
					"jsonFile" : "target-moveit_rviz_plugin_render_tools_autogen-Release-10f5daad067dc91863bf.json",
					"name" : "moveit_rviz_plugin_render_tools_autogen",
					"projectIndex" : 0
				},
				{
					"directoryIndex" : 5,
					"id" : "moveit_trajectory_rviz_plugin::@ea9655eb8b0ab182c77d",
					"jsonFile" : "target-moveit_trajectory_rviz_plugin-Release-1393a3dde4bb88529107.json",
					"name" : "moveit_trajectory_rviz_plugin",
					"projectIndex" : 0
				},
				{
					"directoryIndex" : 5,
					"id" : "moveit_trajectory_rviz_plugin_autogen::@ea9655eb8b0ab182c77d",
					"jsonFile" : "target-moveit_trajectory_rviz_plugin_autogen-Release-ebc195b96c64c8ccf8f8.json",
					"name" : "moveit_trajectory_rviz_plugin_autogen",
					"projectIndex" : 0
				},
				{
					"directoryIndex" : 5,
					"id" : "moveit_trajectory_rviz_plugin_core::@ea9655eb8b0ab182c77d",
					"jsonFile" : "target-moveit_trajectory_rviz_plugin_core-Release-47ac928e79381115f01a.json",
					"name" : "moveit_trajectory_rviz_plugin_core",
					"projectIndex" : 0
				},
				{
					"directoryIndex" : 5,
					"id" : "moveit_trajectory_rviz_plugin_core_autogen::@ea9655eb8b0ab182c77d",
					"jsonFile" : "target-moveit_trajectory_rviz_plugin_core_autogen-Release-aca38adf13df7465c210.json",
					"name" : "moveit_trajectory_rviz_plugin_core_autogen",
					"projectIndex" : 0
				},
				{
					"directoryIndex" : 0,
					"id" : "uninstall::@6890427a1f51a3e7e1df",
					"jsonFile" : "target-uninstall-Release-366abebac8cba1ec2f6e.json",
					"name" : "uninstall",
					"projectIndex" : 0
				}
			]
		}
	],
	"kind" : "codemodel",
	"paths" : 
	{
		"build" : "/home/a/ws_moveit2/build/moveit_ros_visualization",
		"source" : "/home/a/ws_moveit2/src/moveit2/moveit_ros/visualization"
	},
	"version" : 
	{
		"major" : 2,
		"minor" : 3
	}
}
